miniinit/__init__.py
miniinit/config.py
miniinit/env.py
miniinit/util.py
mini_init-0.0.1.dist-info/LICENSE
mini_init-0.0.1.dist-info/METADATA
mini_init-0.0.1.dist-info/WHEEL
mini_init-0.0.1.dist-info/top_level.txt
mini_init-0.0.1.dist-info/RECORD
