Metadata-Version: 2.1
Name: mini-init
Version: 0.0.1
Summary: 简单辅助工具集合: 日志, 配置文件, 环境变量等
Home-page: https://github.com/xiaohuohumax/mini-init
Author: xiaohuohumax
License: MIT
Keywords: mini-init,init,tools,project-init,logging,env,config
Classifier: License :: OSI Approved :: MIT License
Classifier: Programming Language :: Python
Classifier: Programming Language :: Python :: 3.8
Classifier: Programming Language :: Python :: 3.9
Classifier: Programming Language :: Python :: 3.10
Classifier: Programming Language :: Python :: 3.11
Classifier: Programming Language :: Python :: 3.12
Classifier: Programming Language :: Python :: Implementation :: PyPy
Classifier: Topic :: Software Development :: Libraries :: Python Modules
Classifier: Topic :: Utilities
Requires-Python: >=3.8
License-File: LICENSE
Requires-Dist: dacite
Requires-Dist: python-dotenv
Requires-Dist: ruamel.yaml
